imeon_inverter_api/__init__.py
imeon_inverter_api/client.py
imeon_inverter_api/inverter.py
imeon_inverter_api-0.4.1.dist-info/WHEEL
imeon_inverter_api-0.4.1.dist-info/METADATA
imeon_inverter_api-0.4.1.dist-info/licenses/LICENSE
imeon_inverter_api-0.4.1.dist-info/RECORD
