Metadata-Version: 2.1
Name: imeon_inverter_api
Version: 0.4.1
Summary: A standalone API to collect data from the Imeon Energy Inverters. Uses HTTP POST/GET.
License: Apache-2.0
Author-email: Rodrigue Lemaire <developpement@imeon-energy.com>
Requires-Python: >=3.11
Classifier: Operating System :: OS Independent
Classifier: Programming Language :: Python :: 3
Requires-Dist: aiohttp>=3.9.5
Requires-Dist: async-timeout>=4.0.3
Project-URL: Documentation, https://github.com/Imeon-Inverters-for-Home-Assistant/inverter-api/wiki
Project-URL: Homepage, https://github.com/Imeon-Inverters-for-Home-Assistant/inverter-api
Project-URL: Issues, https://github.com/Imeon-Inverters-for-Home-Assistant/inverter-api/issues
